DFRobotUPS/__init__.py
DFRobotUPS/__main__.py
DFRobotUPS/ups.py
DFRobotUPS-0.5.2.dist-info/LICENSE
DFRobotUPS-0.5.2.dist-info/METADATA
DFRobotUPS-0.5.2.dist-info/WHEEL
DFRobotUPS-0.5.2.dist-info/top_level.txt
DFRobotUPS-0.5.2.dist-info/RECORD
