Metadata-Version: 2.1
Name: DFRobotUPS
Version: 0.5.2
Summary: DFRobotUPS module
Home-page: https://github.com/mincebert/DFRobotUPS
Author: Robert Franklin
Project-URL: Bug Reports, https://github.com/mincebert/DFRobotUPS/issues
Project-URL: Source, https://github.com/mincebert/DFRobotUPS
Keywords: dfrobot ups shutdown power raspberrypi pios
Classifier: Development Status :: 4 - Beta
Classifier: Intended Audience :: Developers
Classifier: Topic :: Software Development :: Libraries :: Python Modules
Classifier: License :: OSI Approved :: MIT License
Classifier: Programming Language :: Python :: 3.9
License-File: LICENSE
Requires-Dist: python-daemon
Requires-Dist: smbus
